taskex/__init__.py
taskex/env.py
taskex/run.py
taskex/task.py
taskex/task_runner.py
taskex/models/__init__.py
taskex/models/run_status.py
taskex/models/shell_process.py
taskex/models/task_run.py
taskex/models/task_status.py
taskex/models/task_type.py
taskex/snowflake/__init__.py
taskex/snowflake/constants.py
taskex/snowflake/snowflake.py
taskex/snowflake/snowflake_generator.py
taskex/util/__init__.py
taskex/util/time_parser.py
taskex-0.2.16.dist-info/licenses/LICENSE
taskex-0.2.16.dist-info/METADATA
taskex-0.2.16.dist-info/WHEEL
taskex-0.2.16.dist-info/top_level.txt
taskex-0.2.16.dist-info/RECORD
