Metadata-Version: 2.4
Name: taskex
Version: 0.2.16
Summary: A minimal dependency, pure Python library for running tasks asynchronously
Author-email: Ada Lundhe <adalundhe@lundhe.audio>
License: MIT License
Keywords: tasks,python,async,shell,executor
Classifier: Programming Language :: Python :: 3.11
Classifier: Programming Language :: Python :: 3.12
Classifier: Programming Language :: Python :: 3.13
Classifier: License :: OSI Approved :: MIT License
Classifier: Operating System :: OS Independent
Requires-Python: >=3.11
License-File: LICENSE
Requires-Dist: pydantic
Dynamic: license-file
